jubeatnet/__init__.py
jubeatnet/core.py
jubeatnet/parsers.py
jubeatnet-0.2.0.dist-info/LICENSE.md
jubeatnet-0.2.0.dist-info/WHEEL
jubeatnet-0.2.0.dist-info/METADATA
jubeatnet-0.2.0.dist-info/RECORD
