Metadata-Version: 2.1
Name: jubeatnet
Version: 0.2.0
Summary: End to End solution for analyzing, modelling and visualizing Jubeat songs and player fingering techniques.
Author: Chester
Author-email: chester8991@gmail.com
Requires-Python: >=3.7,<4.0
Classifier: Programming Language :: Python :: 3
Classifier: Programming Language :: Python :: 3.7
Classifier: Programming Language :: Python :: 3.8
Classifier: Programming Language :: Python :: 3.9
Requires-Dist: numpy (>=1.19,<2.0)
